Metadata-Version: 1.0
Name: sirdratuti
Version: 0.3
Summary: lab 2 conflict
Home-page: UNKNOWN
Author: UNKNOWN
Author-email: UNKNOWN
License: UNKNOWN
Platform: UNKNOWN
